openapscontrib.predict-0.0.9-py2.7-nspkg.pth
openapscontrib/predict/__init__.py
openapscontrib/predict/models.py
openapscontrib/predict/predict.py
openapscontrib/predict/version.py
openapscontrib.predict-0.0.9.dist-info/DESCRIPTION.rst
openapscontrib.predict-0.0.9.dist-info/METADATA
openapscontrib.predict-0.0.9.dist-info/metadata.json
openapscontrib.predict-0.0.9.dist-info/namespace_packages.txt
openapscontrib.predict-0.0.9.dist-info/RECORD
openapscontrib.predict-0.0.9.dist-info/top_level.txt
openapscontrib.predict-0.0.9.dist-info/WHEEL
