Metadata-Version: 2.0
Name: openapscontrib.predict
Version: 0.0.9
Summary: openaps predict plugin
Home-page: https://github.com/loudnate/openaps-predict
Author: Nathan Racklyeft
Author-email: loudnate+pypi@gmail.com
License: MIT
Download-URL: http://pypi.python.org/pypi/openapscontrib.predict
Platform: any
Classifier: Development Status :: 3 - Alpha
Classifier: Environment :: Console
Classifier: Intended Audience :: Developers
Classifier: License :: OSI Approved :: MIT License
Classifier: Operating System :: OS Independent
Classifier: Programming Language :: Python :: 2.7
Classifier: Topic :: Documentation
Classifier: Topic :: Utilities
Requires-Dist: openaps
Requires-Dist: python-dateutil
Requires-Dist: numpy
Requires-Dist: scipy
Requires-Dist: functools32
